sstools/__init__.py
sstools/config.py
sstools/environment.py
sagesaver_tools-0.1.2.dist-info/LICENSE
sagesaver_tools-0.1.2.dist-info/METADATA
sagesaver_tools-0.1.2.dist-info/WHEEL
sagesaver_tools-0.1.2.dist-info/top_level.txt
sagesaver_tools-0.1.2.dist-info/RECORD
